marshmallow_br/__init__.py
marshmallow_br/fields.py
marshmallow_br/validate.py
marshmallow_br-0.1.1.dist-info/LICENSE
marshmallow_br-0.1.1.dist-info/METADATA
marshmallow_br-0.1.1.dist-info/WHEEL
marshmallow_br-0.1.1.dist-info/top_level.txt
marshmallow_br-0.1.1.dist-info/RECORD
